diffpy/__init__.py
diffpy/cmi/__init__.py
diffpy/cmi/cli.py
diffpy/cmi/conda.py
diffpy/cmi/fit_tools.py
diffpy/cmi/installer.py
diffpy/cmi/log.py
diffpy/cmi/packsmanager.py
diffpy/cmi/profilesmanager.py
diffpy/cmi/version.py
diffpy/cmi/docs/examples/core/debye-waller/debyemodel.py
diffpy/cmi/docs/examples/core/debye-waller/debyemodelII.py
diffpy/cmi/docs/examples/core/gaussianfit/gaussian.dat
diffpy/cmi/docs/examples/core/gaussianfit/gaussiangenerator.py
diffpy/cmi/docs/examples/core/gaussianfit/gaussianrecipe.py
diffpy/cmi/docs/examples/core/gaussianfit/interface.py
diffpy/cmi/docs/examples/core/gaussianfit/simplerecipe.py
diffpy/cmi/docs/examples/core/gaussianfit/threedoublepeaks.dat
diffpy/cmi/docs/examples/core/gaussianfit/threedoublepeaks.py
diffpy/cmi/docs/examples/core/intensityfit/C60.gr
diffpy/cmi/docs/examples/core/intensityfit/C60.iq
diffpy/cmi/docs/examples/core/intensityfit/C60.stru
diffpy/cmi/docs/examples/core/intensityfit/C60_1.iq
diffpy/cmi/docs/examples/core/intensityfit/C60_2.iq
diffpy/cmi/docs/examples/core/intensityfit/npintensity.py
diffpy/cmi/docs/examples/core/intensityfit/npintensityII.py
diffpy/cmi/docs/examples/core/linefit/03-SrFit-demo-constraints-restraints.ipynb
diffpy/cmi/docs/examples/core/linefit/SrFit-demo-constraints-restraints.py
diffpy/cmi/docs/examples/core/readme/README
diffpy/cmi/docs/examples/pdf/ch03NiModelling/data/Ni.cif
diffpy/cmi/docs/examples/pdf/ch03NiModelling/data/Ni.gr
diffpy/cmi/docs/examples/pdf/ch03NiModelling/data/Pt-nanoparticles.gr
diffpy/cmi/docs/examples/pdf/ch03NiModelling/data/Pt.cif
diffpy/cmi/docs/examples/pdf/ch03NiModelling/exercises/diffpy-cmi/fitBulkNi.ipynb
diffpy/cmi/docs/examples/pdf/ch03NiModelling/exercises/diffpy-cmi/fitNPPt.ipynb
diffpy/cmi/docs/examples/pdf/ch03NiModelling/solutions/diffpy-cmi/fitBulkNi.py
diffpy/cmi/docs/examples/pdf/ch03NiModelling/solutions/diffpy-cmi/fitBulkNi_NPPt_soln2.ipynb
diffpy/cmi/docs/examples/pdf/ch03NiModelling/solutions/diffpy-cmi/fitNPPt.py
diffpy_cmi-3.1.2.dist-info/licenses/AUTHORS.rst
diffpy_cmi-3.1.2.dist-info/licenses/LICENSE.rst
diffpy_cmi-3.1.2.dist-info/METADATA
diffpy_cmi-3.1.2.dist-info/WHEEL
diffpy_cmi-3.1.2.dist-info/entry_points.txt
diffpy_cmi-3.1.2.dist-info/top_level.txt
diffpy_cmi-3.1.2.dist-info/RECORD
