Metadata-Version: 2.4
Name: diffpy.cmi
Version: 3.1.2
Summary: Complex modeling infrastructure: a modular framework for multi-modal modeling of scientific data.
Author-email: Simon Billinge <sb2896@columbia.edu>
Maintainer-email: Simon Billinge <sb2896@columbia.edu>
Project-URL: Homepage, https://github.com/diffpy/diffpy.cmi/
Project-URL: Issues, https://github.com/diffpy/diffpy.cmi/issues/
Keywords: modelling,regression,diffraction,PDF,complex-modeling
Classifier: Development Status :: 5 - Production/Stable
Classifier: Environment :: Console
Classifier: Intended Audience :: Developers
Classifier: Intended Audience :: Science/Research
Classifier: License :: OSI Approved :: BSD License
Classifier: Operating System :: MacOS :: MacOS X
Classifier: Operating System :: Microsoft :: Windows
Classifier: Operating System :: POSIX
Classifier: Operating System :: Unix
Classifier: Programming Language :: Python :: 3.11
Classifier: Programming Language :: Python :: 3.12
Classifier: Programming Language :: Python :: 3.13
Classifier: Topic :: Scientific/Engineering :: Physics
Classifier: Topic :: Scientific/Engineering :: Chemistry
Requires-Python: <3.14,>=3.11
License-File: LICENSE.rst
License-File: AUTHORS.rst
Requires-Dist: packaging
Requires-Dist: PyYAML
Requires-Dist: diffpy.utils
Requires-Dist: diffpy.srfit
Requires-Dist: diffpy.structure
Dynamic: license-file
